mcp_url_downloader/__init__.py
mcp_url_downloader/server.py
mcp_url_downloader-0.1.0.dist-info/WHEEL
mcp_url_downloader-0.1.0.dist-info/entry_points.txt
mcp_url_downloader-0.1.0.dist-info/METADATA
mcp_url_downloader-0.1.0.dist-info/RECORD
