Metadata-Version: 2.3
Name: mcp-url-downloader
Version: 0.1.0
Summary: MCP server that enables AI assistants to download files from URLs to the local filesystem
Keywords: mcp,download,url,file-download,ai-assistant
Author: Dmitry Gilemkhanov
Author-email: Dmitry Gilemkhanov <dima.rize@yandex.ru>
Classifier: Development Status :: 4 - Beta
Classifier: Intended Audience :: Developers
Classifier: License :: OSI Approved :: MIT License
Classifier: Programming Language :: Python :: 3
Classifier: Programming Language :: Python :: 3.11
Classifier: Programming Language :: Python :: 3.12
Classifier: Programming Language :: Python :: 3.13
Requires-Dist: mcp>=1.0.0
Requires-Dist: httpx>=0.27.0
Requires-Dist: pydantic>=2.0.0
Requires-Dist: python-dotenv>=1.0.0
Requires-Python: >=3.11
Project-URL: Homepage, https://github.com/dmitryglhf/mcp-url-downloader
Project-URL: Issues, https://github.com/dmitryglhf/mcp-url-downloader/issues
Project-URL: Repository, https://github.com/dmitryglhf/mcp-url-downloader
